{
  "properties": [
    {
      "name": "com.google.cloud.compute.v1.accelerator-types.enabled",
      "type": "java.lang.Boolean",
      "description": "Auto-configure Google Cloud compute/AcceleratorTypes components.",
      "defaultValue": true
    },
    {
      "name": "com.google.cloud.compute.v1.addresses.enabled",
      "type": "java.lang.Boolean",
      "description": "Auto-configure Google Cloud compute/Addresses components.",
      "defaultValue": true
    },
    {
      "name": "com.google.cloud.compute.v1.autoscalers.enabled",
      "type": "java.lang.Boolean",
      "description": "Auto-configure Google Cloud compute/Autoscalers components.",
      "defaultValue": true
    },
    {
      "name": "com.google.cloud.compute.v1.backend-buckets.enabled",
      "type": "java.lang.Boolean",
      "description": "Auto-configure Google Cloud compute/BackendBuckets components.",
      "defaultValue": true
    },
    {
      "name": "com.google.cloud.compute.v1.backend-services.enabled",
      "type": "java.lang.Boolean",
      "description": "Auto-configure Google Cloud compute/BackendServices components.",
      "defaultValue": true
    },
    {
      "name": "com.google.cloud.compute.v1.disk-types.enabled",
      "type": "java.lang.Boolean",
      "description": "Auto-configure Google Cloud compute/DiskTypes components.",
      "defaultValue": true
    },
    {
      "name": "com.google.cloud.compute.v1.disks.enabled",
      "type": "java.lang.Boolean",
      "description": "Auto-configure Google Cloud compute/Disks components.",
      "defaultValue": true
    },
    {
      "name": "com.google.cloud.compute.v1.external-vpn-gateways.enabled",
      "type": "java.lang.Boolean",
      "description": "Auto-configure Google Cloud compute/ExternalVpnGateways components.",
      "defaultValue": true
    },
    {
      "name": "com.google.cloud.compute.v1.firewall-policies.enabled",
      "type": "java.lang.Boolean",
      "description": "Auto-configure Google Cloud compute/FirewallPolicies components.",
      "defaultValue": true
    },
    {
      "name": "com.google.cloud.compute.v1.firewalls.enabled",
      "type": "java.lang.Boolean",
      "description": "Auto-configure Google Cloud compute/Firewalls components.",
      "defaultValue": true
    },
    {
      "name": "com.google.cloud.compute.v1.forwarding-rules.enabled",
      "type": "java.lang.Boolean",
      "description": "Auto-configure Google Cloud compute/ForwardingRules components.",
      "defaultValue": true
    },
    {
      "name": "com.google.cloud.compute.v1.global-addresses.enabled",
      "type": "java.lang.Boolean",
      "description": "Auto-configure Google Cloud compute/GlobalAddresses components.",
      "defaultValue": true
    },
    {
      "name": "com.google.cloud.compute.v1.global-forwarding-rules.enabled",
      "type": "java.lang.Boolean",
      "description": "Auto-configure Google Cloud compute/GlobalForwardingRules components.",
      "defaultValue": true
    },
    {
      "name": "com.google.cloud.compute.v1.global-network-endpoint-groups.enabled",
      "type": "java.lang.Boolean",
      "description": "Auto-configure Google Cloud compute/GlobalNetworkEndpointGroups components.",
      "defaultValue": true
    },
    {
      "name": "com.google.cloud.compute.v1.global-operations.enabled",
      "type": "java.lang.Boolean",
      "description": "Auto-configure Google Cloud compute/GlobalOperations components.",
      "defaultValue": true
    },
    {
      "name": "com.google.cloud.compute.v1.global-organization-operations.enabled",
      "type": "java.lang.Boolean",
      "description": "Auto-configure Google Cloud compute/GlobalOrganizationOperations components.",
      "defaultValue": true
    },
    {
      "name": "com.google.cloud.compute.v1.global-public-delegated-prefixes.enabled",
      "type": "java.lang.Boolean",
      "description": "Auto-configure Google Cloud compute/GlobalPublicDelegatedPrefixes components.",
      "defaultValue": true
    },
    {
      "name": "com.google.cloud.compute.v1.health-checks.enabled",
      "type": "java.lang.Boolean",
      "description": "Auto-configure Google Cloud compute/HealthChecks components.",
      "defaultValue": true
    },
    {
      "name": "com.google.cloud.compute.v1.image-family-views.enabled",
      "type": "java.lang.Boolean",
      "description": "Auto-configure Google Cloud compute/ImageFamilyViews components.",
      "defaultValue": true
    },
    {
      "name": "com.google.cloud.compute.v1.images.enabled",
      "type": "java.lang.Boolean",
      "description": "Auto-configure Google Cloud compute/Images components.",
      "defaultValue": true
    },
    {
      "name": "com.google.cloud.compute.v1.instance-group-managers.enabled",
      "type": "java.lang.Boolean",
      "description": "Auto-configure Google Cloud compute/InstanceGroupManagers components.",
      "defaultValue": true
    },
    {
      "name": "com.google.cloud.compute.v1.instance-groups.enabled",
      "type": "java.lang.Boolean",
      "description": "Auto-configure Google Cloud compute/InstanceGroups components.",
      "defaultValue": true
    },
    {
      "name": "com.google.cloud.compute.v1.instance-templates.enabled",
      "type": "java.lang.Boolean",
      "description": "Auto-configure Google Cloud compute/InstanceTemplates components.",
      "defaultValue": true
    },
    {
      "name": "com.google.cloud.compute.v1.instances.enabled",
      "type": "java.lang.Boolean",
      "description": "Auto-configure Google Cloud compute/Instances components.",
      "defaultValue": true
    },
    {
      "name": "com.google.cloud.compute.v1.interconnect-attachments.enabled",
      "type": "java.lang.Boolean",
      "description": "Auto-configure Google Cloud compute/InterconnectAttachments components.",
      "defaultValue": true
    },
    {
      "name": "com.google.cloud.compute.v1.interconnect-locations.enabled",
      "type": "java.lang.Boolean",
      "description": "Auto-configure Google Cloud compute/InterconnectLocations components.",
      "defaultValue": true
    },
    {
      "name": "com.google.cloud.compute.v1.interconnects.enabled",
      "type": "java.lang.Boolean",
      "description": "Auto-configure Google Cloud compute/Interconnects components.",
      "defaultValue": true
    },
    {
      "name": "com.google.cloud.compute.v1.license-codes.enabled",
      "type": "java.lang.Boolean",
      "description": "Auto-configure Google Cloud compute/LicenseCodes components.",
      "defaultValue": true
    },
    {
      "name": "com.google.cloud.compute.v1.licenses.enabled",
      "type": "java.lang.Boolean",
      "description": "Auto-configure Google Cloud compute/Licenses components.",
      "defaultValue": true
    },
    {
      "name": "com.google.cloud.compute.v1.machine-images.enabled",
      "type": "java.lang.Boolean",
      "description": "Auto-configure Google Cloud compute/MachineImages components.",
      "defaultValue": true
    },
    {
      "name": "com.google.cloud.compute.v1.machine-types.enabled",
      "type": "java.lang.Boolean",
      "description": "Auto-configure Google Cloud compute/MachineTypes components.",
      "defaultValue": true
    },
    {
      "name": "com.google.cloud.compute.v1.network-attachments.enabled",
      "type": "java.lang.Boolean",
      "description": "Auto-configure Google Cloud compute/NetworkAttachments components.",
      "defaultValue": true
    },
    {
      "name": "com.google.cloud.compute.v1.network-edge-security-services.enabled",
      "type": "java.lang.Boolean",
      "description": "Auto-configure Google Cloud compute/NetworkEdgeSecurityServices components.",
      "defaultValue": true
    },
    {
      "name": "com.google.cloud.compute.v1.network-endpoint-groups.enabled",
      "type": "java.lang.Boolean",
      "description": "Auto-configure Google Cloud compute/NetworkEndpointGroups components.",
      "defaultValue": true
    },
    {
      "name": "com.google.cloud.compute.v1.network-firewall-policies.enabled",
      "type": "java.lang.Boolean",
      "description": "Auto-configure Google Cloud compute/NetworkFirewallPolicies components.",
      "defaultValue": true
    },
    {
      "name": "com.google.cloud.compute.v1.networks.enabled",
      "type": "java.lang.Boolean",
      "description": "Auto-configure Google Cloud compute/Networks components.",
      "defaultValue": true
    },
    {
      "name": "com.google.cloud.compute.v1.node-groups.enabled",
      "type": "java.lang.Boolean",
      "description": "Auto-configure Google Cloud compute/NodeGroups components.",
      "defaultValue": true
    },
    {
      "name": "com.google.cloud.compute.v1.node-templates.enabled",
      "type": "java.lang.Boolean",
      "description": "Auto-configure Google Cloud compute/NodeTemplates components.",
      "defaultValue": true
    },
    {
      "name": "com.google.cloud.compute.v1.node-types.enabled",
      "type": "java.lang.Boolean",
      "description": "Auto-configure Google Cloud compute/NodeTypes components.",
      "defaultValue": true
    },
    {
      "name": "com.google.cloud.compute.v1.packet-mirrorings.enabled",
      "type": "java.lang.Boolean",
      "description": "Auto-configure Google Cloud compute/PacketMirrorings components.",
      "defaultValue": true
    },
    {
      "name": "com.google.cloud.compute.v1.projects.enabled",
      "type": "java.lang.Boolean",
      "description": "Auto-configure Google Cloud compute/Projects components.",
      "defaultValue": true
    },
    {
      "name": "com.google.cloud.compute.v1.public-advertised-prefixes.enabled",
      "type": "java.lang.Boolean",
      "description": "Auto-configure Google Cloud compute/PublicAdvertisedPrefixes components.",
      "defaultValue": true
    },
    {
      "name": "com.google.cloud.compute.v1.public-delegated-prefixes.enabled",
      "type": "java.lang.Boolean",
      "description": "Auto-configure Google Cloud compute/PublicDelegatedPrefixes components.",
      "defaultValue": true
    },
    {
      "name": "com.google.cloud.compute.v1.region-autoscalers.enabled",
      "type": "java.lang.Boolean",
      "description": "Auto-configure Google Cloud compute/RegionAutoscalers components.",
      "defaultValue": true
    },
    {
      "name": "com.google.cloud.compute.v1.region-backend-services.enabled",
      "type": "java.lang.Boolean",
      "description": "Auto-configure Google Cloud compute/RegionBackendServices components.",
      "defaultValue": true
    },
    {
      "name": "com.google.cloud.compute.v1.region-commitments.enabled",
      "type": "java.lang.Boolean",
      "description": "Auto-configure Google Cloud compute/RegionCommitments components.",
      "defaultValue": true
    },
    {
      "name": "com.google.cloud.compute.v1.region-disk-types.enabled",
      "type": "java.lang.Boolean",
      "description": "Auto-configure Google Cloud compute/RegionDiskTypes components.",
      "defaultValue": true
    },
    {
      "name": "com.google.cloud.compute.v1.region-disks.enabled",
      "type": "java.lang.Boolean",
      "description": "Auto-configure Google Cloud compute/RegionDisks components.",
      "defaultValue": true
    },
    {
      "name": "com.google.cloud.compute.v1.region-health-check-services.enabled",
      "type": "java.lang.Boolean",
      "description": "Auto-configure Google Cloud compute/RegionHealthCheckServices components.",
      "defaultValue": true
    },
    {
      "name": "com.google.cloud.compute.v1.region-health-checks.enabled",
      "type": "java.lang.Boolean",
      "description": "Auto-configure Google Cloud compute/RegionHealthChecks components.",
      "defaultValue": true
    },
    {
      "name": "com.google.cloud.compute.v1.region-instance-group-managers.enabled",
      "type": "java.lang.Boolean",
      "description": "Auto-configure Google Cloud compute/RegionInstanceGroupManagers components.",
      "defaultValue": true
    },
    {
      "name": "com.google.cloud.compute.v1.region-instance-groups.enabled",
      "type": "java.lang.Boolean",
      "description": "Auto-configure Google Cloud compute/RegionInstanceGroups components.",
      "defaultValue": true
    },
    {
      "name": "com.google.cloud.compute.v1.region-instance-templates.enabled",
      "type": "java.lang.Boolean",
      "description": "Auto-configure Google Cloud compute/RegionInstanceTemplates components.",
      "defaultValue": true
    },
    {
      "name": "com.google.cloud.compute.v1.region-instances.enabled",
      "type": "java.lang.Boolean",
      "description": "Auto-configure Google Cloud compute/RegionInstances components.",
      "defaultValue": true
    },
    {
      "name": "com.google.cloud.compute.v1.region-network-endpoint-groups.enabled",
      "type": "java.lang.Boolean",
      "description": "Auto-configure Google Cloud compute/RegionNetworkEndpointGroups components.",
      "defaultValue": true
    },
    {
      "name": "com.google.cloud.compute.v1.region-network-firewall-policies.enabled",
      "type": "java.lang.Boolean",
      "description": "Auto-configure Google Cloud compute/RegionNetworkFirewallPolicies components.",
      "defaultValue": true
    },
    {
      "name": "com.google.cloud.compute.v1.region-notification-endpoints.enabled",
      "type": "java.lang.Boolean",
      "description": "Auto-configure Google Cloud compute/RegionNotificationEndpoints components.",
      "defaultValue": true
    },
    {
      "name": "com.google.cloud.compute.v1.region-operations.enabled",
      "type": "java.lang.Boolean",
      "description": "Auto-configure Google Cloud compute/RegionOperations components.",
      "defaultValue": true
    },
    {
      "name": "com.google.cloud.compute.v1.region-security-policies.enabled",
      "type": "java.lang.Boolean",
      "description": "Auto-configure Google Cloud compute/RegionSecurityPolicies components.",
      "defaultValue": true
    },
    {
      "name": "com.google.cloud.compute.v1.region-ssl-certificates.enabled",
      "type": "java.lang.Boolean",
      "description": "Auto-configure Google Cloud compute/RegionSslCertificates components.",
      "defaultValue": true
    },
    {
      "name": "com.google.cloud.compute.v1.region-ssl-policies.enabled",
      "type": "java.lang.Boolean",
      "description": "Auto-configure Google Cloud compute/RegionSslPolicies components.",
      "defaultValue": true
    },
    {
      "name": "com.google.cloud.compute.v1.region-target-http-proxies.enabled",
      "type": "java.lang.Boolean",
      "description": "Auto-configure Google Cloud compute/RegionTargetHttpProxies components.",
      "defaultValue": true
    },
    {
      "name": "com.google.cloud.compute.v1.region-target-https-proxies.enabled",
      "type": "java.lang.Boolean",
      "description": "Auto-configure Google Cloud compute/RegionTargetHttpsProxies components.",
      "defaultValue": true
    },
    {
      "name": "com.google.cloud.compute.v1.region-target-tcp-proxies.enabled",
      "type": "java.lang.Boolean",
      "description": "Auto-configure Google Cloud compute/RegionTargetTcpProxies components.",
      "defaultValue": true
    },
    {
      "name": "com.google.cloud.compute.v1.region-url-maps.enabled",
      "type": "java.lang.Boolean",
      "description": "Auto-configure Google Cloud compute/RegionUrlMaps components.",
      "defaultValue": true
    },
    {
      "name": "com.google.cloud.compute.v1.regions.enabled",
      "type": "java.lang.Boolean",
      "description": "Auto-configure Google Cloud compute/Regions components.",
      "defaultValue": true
    },
    {
      "name": "com.google.cloud.compute.v1.reservations.enabled",
      "type": "java.lang.Boolean",
      "description": "Auto-configure Google Cloud compute/Reservations components.",
      "defaultValue": true
    },
    {
      "name": "com.google.cloud.compute.v1.resource-policies.enabled",
      "type": "java.lang.Boolean",
      "description": "Auto-configure Google Cloud compute/ResourcePolicies components.",
      "defaultValue": true
    },
    {
      "name": "com.google.cloud.compute.v1.routers.enabled",
      "type": "java.lang.Boolean",
      "description": "Auto-configure Google Cloud compute/Routers components.",
      "defaultValue": true
    },
    {
      "name": "com.google.cloud.compute.v1.routes.enabled",
      "type": "java.lang.Boolean",
      "description": "Auto-configure Google Cloud compute/Routes components.",
      "defaultValue": true
    },
    {
      "name": "com.google.cloud.compute.v1.security-policies.enabled",
      "type": "java.lang.Boolean",
      "description": "Auto-configure Google Cloud compute/SecurityPolicies components.",
      "defaultValue": true
    },
    {
      "name": "com.google.cloud.compute.v1.service-attachments.enabled",
      "type": "java.lang.Boolean",
      "description": "Auto-configure Google Cloud compute/ServiceAttachments components.",
      "defaultValue": true
    },
    {
      "name": "com.google.cloud.compute.v1.snapshots.enabled",
      "type": "java.lang.Boolean",
      "description": "Auto-configure Google Cloud compute/Snapshots components.",
      "defaultValue": true
    },
    {
      "name": "com.google.cloud.compute.v1.ssl-certificates.enabled",
      "type": "java.lang.Boolean",
      "description": "Auto-configure Google Cloud compute/SslCertificates components.",
      "defaultValue": true
    },
    {
      "name": "com.google.cloud.compute.v1.ssl-policies.enabled",
      "type": "java.lang.Boolean",
      "description": "Auto-configure Google Cloud compute/SslPolicies components.",
      "defaultValue": true
    },
    {
      "name": "com.google.cloud.compute.v1.subnetworks.enabled",
      "type": "java.lang.Boolean",
      "description": "Auto-configure Google Cloud compute/Subnetworks components.",
      "defaultValue": true
    },
    {
      "name": "com.google.cloud.compute.v1.target-grpc-proxies.enabled",
      "type": "java.lang.Boolean",
      "description": "Auto-configure Google Cloud compute/TargetGrpcProxies components.",
      "defaultValue": true
    },
    {
      "name": "com.google.cloud.compute.v1.target-http-proxies.enabled",
      "type": "java.lang.Boolean",
      "description": "Auto-configure Google Cloud compute/TargetHttpProxies components.",
      "defaultValue": true
    },
    {
      "name": "com.google.cloud.compute.v1.target-https-proxies.enabled",
      "type": "java.lang.Boolean",
      "description": "Auto-configure Google Cloud compute/TargetHttpsProxies components.",
      "defaultValue": true
    },
    {
      "name": "com.google.cloud.compute.v1.target-instances.enabled",
      "type": "java.lang.Boolean",
      "description": "Auto-configure Google Cloud compute/TargetInstances components.",
      "defaultValue": true
    },
    {
      "name": "com.google.cloud.compute.v1.target-pools.enabled",
      "type": "java.lang.Boolean",
      "description": "Auto-configure Google Cloud compute/TargetPools components.",
      "defaultValue": true
    },
    {
      "name": "com.google.cloud.compute.v1.target-ssl-proxies.enabled",
      "type": "java.lang.Boolean",
      "description": "Auto-configure Google Cloud compute/TargetSslProxies components.",
      "defaultValue": true
    },
    {
      "name": "com.google.cloud.compute.v1.target-tcp-proxies.enabled",
      "type": "java.lang.Boolean",
      "description": "Auto-configure Google Cloud compute/TargetTcpProxies components.",
      "defaultValue": true
    },
    {
      "name": "com.google.cloud.compute.v1.target-vpn-gateways.enabled",
      "type": "java.lang.Boolean",
      "description": "Auto-configure Google Cloud compute/TargetVpnGateways components.",
      "defaultValue": true
    },
    {
      "name": "com.google.cloud.compute.v1.url-maps.enabled",
      "type": "java.lang.Boolean",
      "description": "Auto-configure Google Cloud compute/UrlMaps components.",
      "defaultValue": true
    },
    {
      "name": "com.google.cloud.compute.v1.vpn-gateways.enabled",
      "type": "java.lang.Boolean",
      "description": "Auto-configure Google Cloud compute/VpnGateways components.",
      "defaultValue": true
    },
    {
      "name": "com.google.cloud.compute.v1.vpn-tunnels.enabled",
      "type": "java.lang.Boolean",
      "description": "Auto-configure Google Cloud compute/VpnTunnels components.",
      "defaultValue": true
    },
    {
      "name": "com.google.cloud.compute.v1.zone-operations.enabled",
      "type": "java.lang.Boolean",
      "description": "Auto-configure Google Cloud compute/ZoneOperations components.",
      "defaultValue": true
    },
    {
      "name": "com.google.cloud.compute.v1.zones.enabled",
      "type": "java.lang.Boolean",
      "description": "Auto-configure Google Cloud compute/Zones components.",
      "defaultValue": true
    }
  ]
}